{
  "maps": [
    {
      "id": "wynnal",
      "title": "Wynnal",
      "description": "Original demo terrain with biomes and overlays.",
      "filename": "wynnal-terrain.wyn",
      "status": "available",
      "date": "Nov 2025",
      "thumbnail": "maps/thumbnails/wynnal.png"
    },
    {
      "id": "british-isles",
      "title": "British Isles",
      "description": "Heightmap-derived terrain with cities, mountain markers, and a satellite overlay texture.",
      "filename": "british-isles-terrain.wyn",
      "status": "available",
      "date": "2026-02-07 22:17",
      "thumbnail": "maps/thumbnails/british-isles.png"
    },
    {
      "id": "fortress",
      "title": "Fortress",
      "description": "Stylized fortress sample terrain.",
      "filename": "fortress.wyn",
      "status": "available",
      "date": "Nov 2025",
      "thumbnail": "maps/thumbnails/fortress.png"
    },
    {
      "id": "north-america",
      "title": "North America",
      "description": "4096x4096 North America terrain with biomes, mountain ranges, borders, capitals, and high points.",
      "filename": "north-america-terrain.wyn",
      "status": "available",
      "date": "2026-02-09",
      "thumbnail": "maps/thumbnails/north-america.png"
    }
  ]
}
